{"cameraMode":{"drawMode":0,"name":"Shaded","section":"Shading Mode"},"sceneLighting":false,"audioPlay":false,"sceneViewState":{"m_AlwaysRefresh":false,"showFog":true,"showSkybox":false,"showFlares":true,"showImageEffects":true,"showParticleSystems":true,"showVisualEffectGraphs":true,"m_FxEnabled":true},"in2DMode":false,"pivot":{"x":0.0,"y":0.1139630526304245,"z":0.0028874874114990236},"rotation":{"x":-0.04379138723015785,"y":0.012584853917360306,"z":-0.0005525468732230365,"w":-0.9989379048347473},"size":0.5273283123970032,"orthographic":false}